[
  {
    "index":1,
    "section":1,
    "id":"null",
    "x":1254,
    "y":323,
    "w":85,
    "h":177,
    "bx":1299,
    "by":368,
    "r":10,
    "tx":3033,
    "ty":700,
    "attack":false,
    "throwing":false,
    "hide":false,
    "killed":false,
    "yPosTarget":393,
    "standingurl":"http://s3-us-west-2.amazonaws.com/whodic/who_6-s.png",
    "throwingurl":"http://s3-us-west-2.amazonaws.com/whodic/who_6-t.png",
    "killedurl":"http://s3-us-west-2.amazonaws.com/whodic/who_6-d.png"
  },
  {
    "index":2,
    "section":1,
    "id":"null",
    "x":1341,
    "y":313,
    "w":59,
    "h":145,
    "bx":1386,
    "by":358,
    "r":10,
    "tx":2766,
    "ty":700,
    "attack":false,
    "throwing":false,
    "hide":false,
    "killed":false,
    "yPosTarget":383,
    "standingurl":"http://s3-us-west-2.amazonaws.com/whodic/who_18-s.png",
    "throwingurl":"http://s3-us-west-2.amazonaws.com/whodic/who_18-t.png",
    "killedurl":"http://s3-us-west-2.amazonaws.com/whodic/who_18-d.png"
  },
  {
    "index":3,
    "section":1,
    "id":"null",
    "x":1384,
    "y":279,
    "w":66,
    "h":152,
    "bx":1429,
    "by":324,
    "r":10,
    "tx":3072,
    "ty":700,
    "attack":false,
    "throwing":false,
    "hide":false,
    "killed":false,
    "yPosTarget":349,
    "standingurl":"http://s3-us-west-2.amazonaws.com/whodic/who_32-s.png",
    "throwingurl":"http://s3-us-west-2.amazonaws.com/whodic/who_32-t.png",
    "killedurl":"http://s3-us-west-2.amazonaws.com/whodic/who_32-d.png"
  },
  {
    "index":4,
    "section":1,
    "id":"null",
    "x":1452,
    "y":237,
    "w":62,
    "h":148,
    "bx":1497,
    "by":282,
    "r":10,
    "tx":3127,
    "ty":700,
    "attack":false,
    "throwing":false,
    "hide":false,
    "killed":false,
    "yPosTarget":307,
    "standingurl":"http://s3-us-west-2.amazonaws.com/whodic/who_55-s.png",
    "throwingurl":"http://s3-us-west-2.amazonaws.com/whodic/who_55-t.png",
    "killedurl":"http://s3-us-west-2.amazonaws.com/whodic/who_55-d.png"
  },
  {
    "index":5,
    "section":1,
    "id":"null",
    "x":1508,
    "y":226,
    "w":81,
    "h":168,
    "bx":1553,
    "by":271,
    "r":10,
    "tx":2905,
    "ty":700,
    "attack":false,
    "throwing":false,
    "hide":false,
    "killed":false,
    "yPosTarget":296,
    "standingurl":"http://s3-us-west-2.amazonaws.com/whodic/who_47-s.png",
    "throwingurl":"http://s3-us-west-2.amazonaws.com/whodic/who_47-t.png",
    "killedurl":"http://s3-us-west-2.amazonaws.com/whodic/who_47-d.png"
  },
  {
    "index":6,
    "section":1,
    "id":"null",
    "x":1578,
    "y":191,
    "w":70,
    "h":184,
    "bx":1623,
    "by":236,
    "r":10,
    "tx":3062,
    "ty":700,
    "attack":false,
    "throwing":false,
    "hide":false,
    "killed":false,
    "yPosTarget":261,
    "standingurl":"http://s3-us-west-2.amazonaws.com/whodic/who_12-s.png",
    "throwingurl":"http://s3-us-west-2.amazonaws.com/whodic/who_12-t.png",
    "killedurl":"http://s3-us-west-2.amazonaws.com/whodic/who_12-d.png"
  },
  {
    "index":7,
    "section":1,
    "id":"null",
    "x":1635,
    "y":182,
    "w":85,
    "h":155,
    "bx":1680,
    "by":227,
    "r":10,
    "tx":2951,
    "ty":700,
    "attack":false,
    "throwing":false,
    "hide":false,
    "killed":false,
    "yPosTarget":252,
    "standingurl":"http://s3-us-west-2.amazonaws.com/whodic/who_11-s.png",
    "throwingurl":"http://s3-us-west-2.amazonaws.com/whodic/who_11-t.png",
    "killedurl":"http://s3-us-west-2.amazonaws.com/whodic/who_11-d.png"
  },
  {
    "index":8,
    "section":1,
    "id":"null",
    "x":1703,
    "y":146,
    "w":77,
    "h":177,
    "bx":1748,
    "by":191,
    "r":10,
    "tx":2603,
    "ty":700,
    "attack":false,
    "throwing":false,
    "hide":false,
    "killed":false,
    "yPosTarget":216,
    "standingurl":"http://s3-us-west-2.amazonaws.com/whodic/who_20-s.png",
    "throwingurl":"http://s3-us-west-2.amazonaws.com/whodic/who_20-t.png",
    "killedurl":"http://s3-us-west-2.amazonaws.com/whodic/who_20-d.png"
  },
  {
    "index":9,
    "section":1,
    "id":"null",
    "x":1774,
    "y":116,
    "w":84,
    "h":203,
    "bx":1819,
    "by":161,
    "r":10,
    "tx":3052,
    "ty":700,
    "attack":false,
    "throwing":false,
    "hide":false,
    "killed":false,
    "yPosTarget":186,
    "standingurl":"http://s3-us-west-2.amazonaws.com/whodic/who_53-s.png",
    "throwingurl":"http://s3-us-west-2.amazonaws.com/whodic/who_53-t.png",
    "killedurl":"http://s3-us-west-2.amazonaws.com/whodic/who_53-d.png"
  },
  {
    "index":10,
    "section":1,
    "id":"null",
    "x":1849,
    "y":84,
    "w":74,
    "h":227,
    "bx":1894,
    "by":129,
    "r":10,
    "tx":2824,
    "ty":700,
    "attack":false,
    "throwing":false,
    "hide":false,
    "killed":false,
    "yPosTarget":154,
    "standingurl":"http://s3-us-west-2.amazonaws.com/whodic/who_54-s.png",
    "throwingurl":"http://s3-us-west-2.amazonaws.com/whodic/who_54-t.png",
    "killedurl":"http://s3-us-west-2.amazonaws.com/whodic/who_54-d.png"
  },
  {
    "index":11,
    "section":1,
    "id":"null",
    "x":1925,
    "y":114,
    "w":60,
    "h":147,
    "bx":1970,
    "by":159,
    "r":10,
    "tx":2872,
    "ty":700,
    "attack":false,
    "throwing":false,
    "hide":false,
    "killed":false,
    "yPosTarget":184,
    "standingurl":"http://s3-us-west-2.amazonaws.com/whodic/who_2-s.png",
    "throwingurl":"http://s3-us-west-2.amazonaws.com/whodic/who_2-t.png",
    "killedurl":"http://s3-us-west-2.amazonaws.com/whodic/who_2-d.png"
  },
  {
    "index":12,
    "section":1,
    "id":"null",
    "x":1994,
    "y":106,
    "w":60,
    "h":152,
    "bx":2039,
    "by":151,
    "r":10,
    "tx":2783,
    "ty":700,
    "attack":false,
    "throwing":false,
    "hide":false,
    "killed":false,
    "yPosTarget":176,
    "standingurl":"http://s3-us-west-2.amazonaws.com/whodic/who_4-s.png",
    "throwingurl":"http://s3-us-west-2.amazonaws.com/whodic/who_4-t.png",
    "killedurl":"http://s3-us-west-2.amazonaws.com/whodic/who_4-d.png"
  },
  {
    "index":13,
    "section":1,
    "id":"null",
    "x":2044,
    "y":97,
    "w":96,
    "h":170,
    "bx":2089,
    "by":142,
    "r":10,
    "tx":2668,
    "ty":700,
    "attack":false,
    "throwing":false,
    "hide":false,
    "killed":false,
    "yPosTarget":167,
    "standingurl":"http://s3-us-west-2.amazonaws.com/whodic/who_52-s.png",
    "throwingurl":"http://s3-us-west-2.amazonaws.com/whodic/who_52-t.png",
    "killedurl":"http://s3-us-west-2.amazonaws.com/whodic/who_52-d.png"
  },
  {
    "index":14,
    "section":1,
    "id":"null",
    "x":2137,
    "y":88,
    "w":69,
    "h":160,
    "bx":2182,
    "by":133,
    "r":10,
    "tx":2989,
    "ty":700,
    "attack":false,
    "throwing":false,
    "hide":false,
    "killed":false,
    "yPosTarget":158,
    "standingurl":"http://s3-us-west-2.amazonaws.com/whodic/who_51-s.png",
    "throwingurl":"http://s3-us-west-2.amazonaws.com/whodic/who_51-t.png",
    "killedurl":"http://s3-us-west-2.amazonaws.com/whodic/who_51-d.png"
  },
  {
    "index":15,
    "section":1,
    "id":"null",
    "x":2190,
    "y":82,
    "w":98,
    "h":171,
    "bx":2235,
    "by":127,
    "r":10,
    "tx":3191,
    "ty":700,
    "attack":false,
    "throwing":false,
    "hide":false,
    "killed":false,
    "yPosTarget":152,
    "standingurl":"http://s3-us-west-2.amazonaws.com/whodic/who_43-s.png",
    "throwingurl":"http://s3-us-west-2.amazonaws.com/whodic/who_43-t.png",
    "killedurl":"http://s3-us-west-2.amazonaws.com/whodic/who_43-d.png"
  },
  {
    "index":16,
    "section":1,
    "id":"null",
    "x":2286,
    "y":78,
    "w":71,
    "h":144,
    "bx":2331,
    "by":123,
    "r":10,
    "tx":2719,
    "ty":700,
    "attack":false,
    "throwing":false,
    "hide":false,
    "killed":false,
    "yPosTarget":148,
    "standingurl":"http://s3-us-west-2.amazonaws.com/whodic/who_3-s.png",
    "throwingurl":"http://s3-us-west-2.amazonaws.com/whodic/who_3-t.png",
    "killedurl":"http://s3-us-west-2.amazonaws.com/whodic/who_3-d.png"
  },
  {
    "index":17,
    "section":1,
    "id":"null",
    "x":2346,
    "y":57,
    "w":72,
    "h":174,
    "bx":2391,
    "by":102,
    "r":10,
    "tx":2941,
    "ty":700,
    "attack":false,
    "throwing":false,
    "hide":false,
    "killed":false,
    "yPosTarget":127,
    "standingurl":"http://s3-us-west-2.amazonaws.com/whodic/who_5-s.png",
    "throwingurl":"http://s3-us-west-2.amazonaws.com/whodic/who_5-t.png",
    "killedurl":"http://s3-us-west-2.amazonaws.com/whodic/who_5-d.png"
  },
  {
    "index":18,
    "section":1,
    "id":"null",
    "x":2399,
    "y":95,
    "w":72,
    "h":146,
    "bx":2444,
    "by":140,
    "r":10,
    "tx":2785,
    "ty":700,
    "attack":false,
    "throwing":false,
    "hide":false,
    "killed":false,
    "yPosTarget":165,
    "standingurl":"http://s3-us-west-2.amazonaws.com/whodic/who_9-s.png",
    "throwingurl":"http://s3-us-west-2.amazonaws.com/whodic/who_9-t.png",
    "killedurl":"http://s3-us-west-2.amazonaws.com/whodic/who_9-d.png"
  },
  {
    "index":19,
    "section":1,
    "id":"null",
    "x":1499,
    "y":455,
    "w":64,
    "h":154,
    "bx":1544,
    "by":500,
    "r":10,
    "tx":2947,
    "ty":700,
    "attack":false,
    "throwing":false,
    "hide":false,
    "killed":false,
    "yPosTarget":525,
    "standingurl":"http://s3-us-west-2.amazonaws.com/whodic/who_30-s.png",
    "throwingurl":"http://s3-us-west-2.amazonaws.com/whodic/who_30-t.png",
    "killedurl":"http://s3-us-west-2.amazonaws.com/whodic/who_30-d.png"
  },
  {
    "index":20,
    "section":1,
    "id":"null",
    "x":1587,
    "y":418,
    "w":84,
    "h":186,
    "bx":1632,
    "by":463,
    "r":10,
    "tx":2767,
    "ty":700,
    "attack":false,
    "throwing":false,
    "hide":false,
    "killed":false,
    "yPosTarget":488,
    "standingurl":"http://s3-us-west-2.amazonaws.com/whodic/who_7-s.png",
    "throwingurl":"http://s3-us-west-2.amazonaws.com/whodic/who_7-t.png",
    "killedurl":"http://s3-us-west-2.amazonaws.com/whodic/who_7-d.png"
  },
  {
    "index":21,
    "section":1,
    "id":"null",
    "x":1643,
    "y":388,
    "w":89,
    "h":185,
    "bx":1688,
    "by":433,
    "r":10,
    "tx":2756,
    "ty":700,
    "attack":false,
    "throwing":false,
    "hide":false,
    "killed":false,
    "yPosTarget":458,
    "standingurl":"http://s3-us-west-2.amazonaws.com/whodic/who_40-s.png",
    "throwingurl":"http://s3-us-west-2.amazonaws.com/whodic/who_40-t.png",
    "killedurl":"http://s3-us-west-2.amazonaws.com/whodic/who_40-d.png"
  },
  {
    "index":22,
    "section":1,
    "id":"null",
    "x":1721,
    "y":377,
    "w":73,
    "h":167,
    "bx":1766,
    "by":422,
    "r":10,
    "tx":3113,
    "ty":700,
    "attack":false,
    "throwing":false,
    "hide":false,
    "killed":false,
    "yPosTarget":447,
    "standingurl":"http://s3-us-west-2.amazonaws.com/whodic/who_44-s.png",
    "throwingurl":"http://s3-us-west-2.amazonaws.com/whodic/who_44-t.png",
    "killedurl":"http://s3-us-west-2.amazonaws.com/whodic/who_44-d.png"
  },
  {
    "index":23,
    "section":1,
    "id":"null",
    "x":1780,
    "y":330,
    "w":78,
    "h":181,
    "bx":1825,
    "by":375,
    "r":10,
    "tx":3058,
    "ty":700,
    "attack":false,
    "throwing":false,
    "hide":false,
    "killed":false,
    "yPosTarget":400,
    "standingurl":"http://s3-us-west-2.amazonaws.com/whodic/who_45-s.png",
    "throwingurl":"http://s3-us-west-2.amazonaws.com/whodic/who_45-t.png",
    "killedurl":"http://s3-us-west-2.amazonaws.com/whodic/who_45-d.png"
  },
  {
    "index":24,
    "section":1,
    "id":"null",
    "x":1872,
    "y":347,
    "w":67,
    "h":117,
    "bx":1917,
    "by":392,
    "r":10,
    "tx":2717,
    "ty":700,
    "attack":false,
    "throwing":false,
    "hide":false,
    "killed":false,
    "yPosTarget":417,
    "standingurl":"http://s3-us-west-2.amazonaws.com/whodic/who_48-s.png",
    "throwingurl":"http://s3-us-west-2.amazonaws.com/whodic/who_48-t.png",
    "killedurl":"http://s3-us-west-2.amazonaws.com/whodic/who_48-d.png"
  },
  {
    "index":25,
    "section":1,
    "id":"null",
    "x":1937,
    "y":317,
    "w":76,
    "h":158,
    "bx":1982,
    "by":362,
    "r":10,
    "tx":2616,
    "ty":700,
    "attack":false,
    "throwing":false,
    "hide":false,
    "killed":false,
    "yPosTarget":387,
    "standingurl":"http://s3-us-west-2.amazonaws.com/whodic/who_42-s.png",
    "throwingurl":"http://s3-us-west-2.amazonaws.com/whodic/who_42-t.png",
    "killedurl":"http://s3-us-west-2.amazonaws.com/whodic/who_42-d.png"
  },
  {
    "index":26,
    "section":1,
    "id":"null",
    "x":2409,
    "y":263,
    "w":59,
    "h":126,
    "bx":1982,
    "by":308,
    "r":10,
    "tx":3062,
    "ty":700,
    "attack":false,
    "throwing":false,
    "hide":false,
    "killed":false,
    "yPosTarget":333,
    "standingurl":"http://s3-us-west-2.amazonaws.com/whodic/who_23-s.png",
    "throwingurl":"http://s3-us-west-2.amazonaws.com/whodic/who_23-t.png",
    "killedurl":"http://s3-us-west-2.amazonaws.com/whodic/who_23-d.png"
  },
  {
    "index":27,
    "section":1,
    "id":"null",
    "x":2496,
    "y":216,
    "w":57,
    "h":166,
    "bx":2454,
    "by":261,
    "r":10,
    "tx":3181,
    "ty":700,
    "attack":false,
    "throwing":false,
    "hide":false,
    "killed":false,
    "yPosTarget":286,
    "standingurl":"http://s3-us-west-2.amazonaws.com/whodic/who_38-s.png",
    "throwingurl":"http://s3-us-west-2.amazonaws.com/whodic/who_38-t.png",
    "killedurl":"http://s3-us-west-2.amazonaws.com/whodic/who_38-d.png"
  },
  {
    "index":28,
    "section":1,
    "id":"null",
    "x":2566,
    "y":218,
    "w":62,
    "h":161,
    "bx":2611,
    "by":263,
    "r":10,
    "tx":2883,
    "ty":700,
    "attack":false,
    "throwing":false,
    "hide":false,
    "killed":false,
    "yPosTarget":288,
    "standingurl":"http://s3-us-west-2.amazonaws.com/whodic/who_39-s.png",
    "throwingurl":"http://s3-us-west-2.amazonaws.com/whodic/who_39-t.png",
    "killedurl":"http://s3-us-west-2.amazonaws.com/whodic/who_39-d.png"
  },
  {
    "index":29,
    "section":1,
    "id":"null",
    "x":2619,
    "y":215,
    "w":86,
    "h":155,
    "bx":2664,
    "by":260,
    "r":10,
    "tx":2856,
    "ty":700,
    "attack":false,
    "throwing":false,
    "hide":false,
    "killed":false,
    "yPosTarget":285,
    "standingurl":"http://s3-us-west-2.amazonaws.com/whodic/who_41-s.png",
    "throwingurl":"http://s3-us-west-2.amazonaws.com/whodic/who_41-t.png",
    "killedurl":"http://s3-us-west-2.amazonaws.com/whodic/who_41-d.png"
  },
  {
    "index":30,
    "section":1,
    "id":"null",
    "x":2702,
    "y":196,
    "w":71,
    "h":156,
    "bx":2747,
    "by":241,
    "r":10,
    "tx":3103,
    "ty":700,
    "attack":false,
    "throwing":false,
    "hide":false,
    "killed":false,
    "yPosTarget":266,
    "standingurl":"http://s3-us-west-2.amazonaws.com/whodic/who_37-s.png",
    "throwingurl":"http://s3-us-west-2.amazonaws.com/whodic/who_37-t.png",
    "killedurl":"http://s3-us-west-2.amazonaws.com/whodic/who_37-d.png"
  },
  {
    "index":31,
    "section":1,
    "id":"null",
    "x":2754,
    "y":191,
    "w":92,
    "h":162,
    "bx":2799,
    "by":236,
    "r":10,
    "tx":2943,
    "ty":700,
    "attack":false,
    "throwing":false,
    "hide":false,
    "killed":false,
    "yPosTarget":261,
    "standingurl":"http://s3-us-west-2.amazonaws.com/whodic/who_36-s.png",
    "throwingurl":"http://s3-us-west-2.amazonaws.com/whodic/who_36-t.png",
    "killedurl":"http://s3-us-west-2.amazonaws.com/whodic/who_36-d.png"
  },
  {
    "index":32,
    "section":1,
    "id":"null",
    "x":2853,
    "y":160,
    "w":72,
    "h":177,
    "bx":2898,
    "by":205,
    "r":10,
    "tx":2791,
    "ty":700,
    "attack":false,
    "throwing":false,
    "hide":false,
    "killed":false,
    "yPosTarget":230,
    "standingurl":"http://s3-us-west-2.amazonaws.com/whodic/who_17-s.png",
    "throwingurl":"http://s3-us-west-2.amazonaws.com/whodic/who_17-t.png",
    "killedurl":"http://s3-us-west-2.amazonaws.com/whodic/who_17-d.png"
  },
  {
    "index":33,
    "section":1,
    "id":"null",
    "x":2934,
    "y":146,
    "w":69,
    "h":193,
    "bx":2979,
    "by":191,
    "r":10,
    "tx":2810,
    "ty":700,
    "attack":false,
    "throwing":false,
    "hide":false,
    "killed":false,
    "yPosTarget":216,
    "standingurl":"http://s3-us-west-2.amazonaws.com/whodic/who_21-s.png",
    "throwingurl":"http://s3-us-west-2.amazonaws.com/whodic/who_21-t.png",
    "killedurl":"http://s3-us-west-2.amazonaws.com/whodic/who_21-d.png"
  },
  {
    "index":34,
    "section":1,
    "id":"null",
    "x":3015,
    "y":178,
    "w":72,
    "h":149,
    "bx":3060,
    "by":223,
    "r":10,
    "tx":2875,
    "ty":700,
    "attack":false,
    "throwing":false,
    "hide":false,
    "killed":false,
    "yPosTarget":248,
    "standingurl":"http://s3-us-west-2.amazonaws.com/whodic/who_31-s.png",
    "throwingurl":"http://s3-us-west-2.amazonaws.com/whodic/who_31-t.png",
    "killedurl":"http://s3-us-west-2.amazonaws.com/whodic/who_31-d.png"
  },
  {
    "index":35,
    "section":1,
    "id":"null",
    "x":1902,
    "y":573,
    "w":66,
    "h":132,
    "bx":1947,
    "by":618,
    "r":10,
    "tx":2735,
    "ty":700,
    "attack":false,
    "throwing":false,
    "hide":false,
    "killed":false,
    "yPosTarget":643,
    "standingurl":"http://s3-us-west-2.amazonaws.com/whodic/who_34-s.png",
    "throwingurl":"http://s3-us-west-2.amazonaws.com/whodic/who_34-t.png",
    "killedurl":"http://s3-us-west-2.amazonaws.com/whodic/who_34-d.png"
  },
  {
    "index":36,
    "section":1,
    "id":"null",
    "x":1973,
    "y":516,
    "w":75,
    "h":171,
    "bx":2018,
    "by":561,
    "r":10,
    "tx":3181,
    "ty":700,
    "attack":false,
    "throwing":false,
    "hide":false,
    "killed":false,
    "yPosTarget":586,
    "standingurl":"http://s3-us-west-2.amazonaws.com/whodic/who_13-s.png",
    "throwingurl":"http://s3-us-west-2.amazonaws.com/whodic/who_13-t.png",
    "killedurl":"http://s3-us-west-2.amazonaws.com/whodic/who_13-d.png"
  },
  {
    "index":37,
    "section":1,
    "id":"null",
    "x":2043,
    "y":474,
    "w":91,
    "h":190,
    "bx":2088,
    "by":519,
    "r":10,
    "tx":2645,
    "ty":700,
    "attack":false,
    "throwing":false,
    "hide":false,
    "killed":false,
    "yPosTarget":544,
    "standingurl":"http://s3-us-west-2.amazonaws.com/whodic/who_49-s.png",
    "throwingurl":"http://s3-us-west-2.amazonaws.com/whodic/who_49-t.png",
    "killedurl":"http://s3-us-west-2.amazonaws.com/whodic/who_49-d.png"
  },
  {
    "index":38,
    "section":1,
    "id":"null",
    "x":2121,
    "y":456,
    "w":71,
    "h":165,
    "bx":2166,
    "by":501,
    "r":10,
    "tx":2715,
    "ty":700,
    "attack":false,
    "throwing":false,
    "hide":false,
    "killed":false,
    "yPosTarget":526,
    "standingurl":"http://s3-us-west-2.amazonaws.com/whodic/who_46-s.png",
    "throwingurl":"http://s3-us-west-2.amazonaws.com/whodic/who_46-t.png",
    "killedurl":"http://s3-us-west-2.amazonaws.com/whodic/who_46-d.png"
  },
  {
    "index":39,
    "section":1,
    "id":"null",
    "x":2182,
    "y":431,
    "w":91,
    "h":177,
    "bx":2227,
    "by":476,
    "r":10,
    "tx":2682,
    "ty":700,
    "attack":false,
    "throwing":false,
    "hide":false,
    "killed":false,
    "yPosTarget":501,
    "standingurl":"http://s3-us-west-2.amazonaws.com/whodic/who_8-s.png",
    "throwingurl":"http://s3-us-west-2.amazonaws.com/whodic/who_8-t.png",
    "killedurl":"http://s3-us-west-2.amazonaws.com/whodic/who_8-d.png"
  },
  {
    "index":40,
    "section":1,
    "id":"null",
    "x":2738,
    "y":441,
    "w":66,
    "h":133,
    "bx":2783,
    "by":486,
    "r":10,
    "tx":2796,
    "ty":700,
    "attack":false,
    "throwing":false,
    "hide":false,
    "killed":false,
    "yPosTarget":511,
    "standingurl":"http://s3-us-west-2.amazonaws.com/whodic/who_19-s.png",
    "throwingurl":"http://s3-us-west-2.amazonaws.com/whodic/who_19-t.png",
    "killedurl":"http://s3-us-west-2.amazonaws.com/whodic/who_19-d.png"
  },
  {
    "index":41,
    "section":1,
    "id":"null",
    "x":2811,
    "y":403,
    "w":76,
    "h":166,
    "bx":2856,
    "by":448,
    "r":10,
    "tx":3127,
    "ty":700,
    "attack":false,
    "throwing":false,
    "hide":false,
    "killed":false,
    "yPosTarget":473,
    "standingurl":"http://s3-us-west-2.amazonaws.com/whodic/who_27-s.png",
    "throwingurl":"http://s3-us-west-2.amazonaws.com/whodic/who_27-t.png",
    "killedurl":"http://s3-us-west-2.amazonaws.com/whodic/who_27-d.png"
  },
  {
    "index":42,
    "section":1,
    "id":"null",
    "x":2890,
    "y":369,
    "w":73,
    "h":177,
    "bx":2935,
    "by":414,
    "r":10,
    "tx":2696,
    "ty":700,
    "attack":false,
    "throwing":false,
    "hide":false,
    "killed":false,
    "yPosTarget":439,
    "standingurl":"http://s3-us-west-2.amazonaws.com/whodic/who_16-s.png",
    "throwingurl":"http://s3-us-west-2.amazonaws.com/whodic/who_16-t.png",
    "killedurl":"http://s3-us-west-2.amazonaws.com/whodic/who_16-d.png"
  },
  {
    "index":43,
    "section":1,
    "id":"null",
    "x":3175,
    "y":480,
    "w":67,
    "h":186,
    "bx":3220,
    "by":525,
    "r":10,
    "tx":3095,
    "ty":700,
    "attack":false,
    "throwing":false,
    "hide":false,
    "killed":false,
    "yPosTarget":550,
    "standingurl":"http://s3-us-west-2.amazonaws.com/whodic/who_22-s.png",
    "throwingurl":"http://s3-us-west-2.amazonaws.com/whodic/who_22-t.png",
    "killedurl":"http://s3-us-west-2.amazonaws.com/whodic/who_22-d.png"
  },
  {
    "index":44,
    "section":1,
    "id":"null",
    "x":3037,
    "y":341,
    "w":83,
    "h":177,
    "bx":3082,
    "by":386,
    "r":10,
    "tx":2651,
    "ty":700,
    "attack":false,
    "throwing":false,
    "hide":false,
    "killed":false,
    "yPosTarget":411,
    "standingurl":"http://s3-us-west-2.amazonaws.com/whodic/who_26-s.png",
    "throwingurl":"http://s3-us-west-2.amazonaws.com/whodic/who_26-t.png",
    "killedurl":"http://s3-us-west-2.amazonaws.com/whodic/who_26-d.png"
  },
  {
    "index":45,
    "section":1,
    "id":"null",
    "x":3122,
    "y":346,
    "w":75,
    "h":149,
    "bx":3167,
    "by":391,
    "r":10,
    "tx":2937,
    "ty":700,
    "attack":false,
    "throwing":false,
    "hide":false,
    "killed":false,
    "yPosTarget":416,
    "standingurl":"http://s3-us-west-2.amazonaws.com/whodic/who_28-s.png",
    "throwingurl":"http://s3-us-west-2.amazonaws.com/whodic/who_28-t.png",
    "killedurl":"http://s3-us-west-2.amazonaws.com/whodic/who_28-d.png"
  }
]